evdm/__init__.py
evdm/core.py
evdm/actors/__init__.py
evdm/actors/debug.py
evdm/actors/audio/__init__.py
evdm/actors/audio/deepgram.py
evdm/actors/audio/microphone.py
evdm/actors/audio/speaker.py
evdm/actors/conversation/__init__.py
evdm/actors/conversation/ollama.py
evdm/actors/conversation/openai.py
evdm-0.3.1.dist-info/METADATA
evdm-0.3.1.dist-info/WHEEL
evdm-0.3.1.dist-info/RECORD
