Metadata-Version: 2.3
Name: evdm
Version: 0.3.1
Summary: Prototype of a Hierarchical Event Bus for building event driven speech conversational AI systems
Requires-Python: >=3.11
Requires-Dist: aioconsole>=0.8.0
Requires-Dist: deepgram-sdk>=3.7.3
Requires-Dist: loguru>=0.7.2
Requires-Dist: numpy>=2.1.0
Requires-Dist: ollama>=0.3.2
Requires-Dist: pyaudio>=0.2.14
Requires-Dist: sounddevice>=0.5.0
Requires-Dist: soundfile
Requires-Dist: websockets>=13.1
